LICENSE.txt
README.md
awesome_sso/__init__.py
awesome_sso/mail/__init__.py
awesome_sso/mail/mailgun.py
awesome_sso/service/__init__.py
awesome_sso/service/depends.py
awesome_sso/service/notification/read_notification.py
awesome_sso/service/notification/schema.py
awesome_sso/service/notification/sync_notification.py
awesome_sso/service/route.py
awesome_sso/service/service_registration.py
awesome_sso/service/settings.py
awesome_sso/service/user/__init__.py
awesome_sso/service/user/schema.py
awesome_sso/service/user/sync_user.py
awesome_sso/store/__init__.py
awesome_sso/store/mongo.py
awesome_sso/util/__init__.py
awesome_sso/util/constant.py
awesome_sso/util/encode.py
awesome_sso/util/jwt.py
awesome_sso/util/response_error_check.py
awesome_sso-0.6.0.dist-info/LICENSE.txt
awesome_sso-0.6.0.dist-info/WHEEL
awesome_sso-0.6.0.dist-info/METADATA
awesome_sso-0.6.0.dist-info/RECORD
