Metadata-Version: 2.1
Name: awesome-sso
Version: 0.6.0
Summary: sso general utility for services connected to sso
Home-page: https://github.com/MoBagel/awesome-sso
License: Apache-2.0
Author: Schwannden Kuo
Author-email: schwannden@mobagel.com
Requires-Python: >=3.8,<4.0
Classifier: Development Status :: 1 - Planning
Classifier: Intended Audience :: Developers
Classifier: Intended Audience :: Information Technology
Classifier: License :: OSI Approved :: Apache Software License
Classifier: Operating System :: OS Independent
Classifier: Programming Language :: Python :: 3
Classifier: Programming Language :: Python :: 3.10
Classifier: Programming Language :: Python :: 3.8
Classifier: Programming Language :: Python :: 3.9
Classifier: Programming Language :: Python :: Implementation :: PyPy
Classifier: Topic :: Internet
Classifier: Topic :: Internet :: WWW/HTTP
Classifier: Topic :: Software Development :: Libraries
Classifier: Topic :: Software Development :: Libraries :: Application Frameworks
Classifier: Topic :: Software Development :: Libraries :: Python Modules
Requires-Dist: APScheduler (>=3.8.1,<4.0.0)
Requires-Dist: PyJWT (>=2.3.0,<3.0.0)
Requires-Dist: awesome-exception (>=1.1.0,<2.0.0)
Requires-Dist: bcrypt (>=3.2.0,<4.0.0)
Requires-Dist: beanie (>=1.8.0,<2.0.0)
Requires-Dist: cryptography (>=36.0.0,<37.0.0)
Requires-Dist: fastapi (>=0.70.0,<0.71.0)
Requires-Dist: pandas (>=1.3.5,<2.0.0)
Requires-Dist: psutil (>=5.8.0,<6.0.0)
Requires-Dist: pydantic[email] (>=1.8.2,<2.0.0)
Requires-Dist: uvicorn (>=0.16.0,<0.17.0)
